{
	"title": "Skillset",
	"skills": [
		{
			"title": "Front-End Web Development",
			"description": "Crafting Digital Canvases",
			"technologies": [
				"react",
				"svelte",
				"tailwind",
				"bootstrap",
				"typescript",
				"javascript",
				"css",
				"html"
			]
		},
		{
			"title": "Computer Graphics & Game Development",
			"description": "Breathing Life into Pixels",
			"technologies": ["threejs", "aframe", "unity", "godot", "blender"]
		},
		{
			"title": "Back-end Web Development",
			"description": "Sculpting Digital Foundations",
			"technologies": ["laravel", "php", "express", "nodejs", "mongodb", "sql", "mariadb"]
		}
	]
}
